checklist/__init__.py
checklist/macros.py
checklist/plugin.wk
checklist/htdocs/checklist.css
checklist/htdocs/checklist.png
checklist/htdocs/extra.js
checklist/htdocs/menu.css
checklist/htdocs/menu.js
checklist/htdocs/save.js
checklist/upgrades/__init__.py
checklist/upgrades/db2.py
TracChecklist-0.3.0.dist-info/LICENSE
TracChecklist-0.3.0.dist-info/METADATA
TracChecklist-0.3.0.dist-info/WHEEL
TracChecklist-0.3.0.dist-info/entry_points.txt
TracChecklist-0.3.0.dist-info/top_level.txt
TracChecklist-0.3.0.dist-info/RECORD
