Metadata-Version: 2.1
Name: TracChecklist
Version: 0.3.0
Summary: Include checklists in ticket, sourced from wiki pages
Home-page: https://trac-hacks.org/wiki/TracChecklistMacro
Author: Ralph Ewig
Author-email: ralph.ewig@outlyer.space
Project-URL: Bug Tracker, https://trac-hacks.org/report/9?COMPONENT=TracChecklistMacro
Classifier: Programming Language :: Python :: 2.7
Classifier: License :: OSI Approved :: MIT License
Classifier: Operating System :: OS Independent
Classifier: Framework :: Trac
License-File: LICENSE
